airflow/providers/couchbase/__init__.py
airflow/providers/couchbase/get_provider_info.py
airflow/providers/couchbase/hooks/__init__.py
airflow/providers/couchbase/hooks/couchbase.py
airflow/providers/couchbase/operators/__init__.py
airflow/providers/couchbase/operators/couchbase.py
airflow_provider_couchbase-1.0.0.dist-info/LICENSE
airflow_provider_couchbase-1.0.0.dist-info/METADATA
airflow_provider_couchbase-1.0.0.dist-info/WHEEL
airflow_provider_couchbase-1.0.0.dist-info/top_level.txt
airflow_provider_couchbase-1.0.0.dist-info/RECORD
