Metadata-Version: 2.1
Name: airflow-provider-couchbase
Version: 1.0.0
Summary: provide couchbase access through airflow.
Home-page: https://github.com/aymen-ayadi/airflow-provider-couchbase
License-File: LICENSE
